{
  "name": "Big Hotspot Loot T3",
  "type": "BigHotspotLoot_T3_C",
  "lootTemplate": "BigHotspotLoot_T3_C",
  "category": "Resource",
  "tier": "T3",
  "drops": [
    {
      "name": "Ceramic-Tipped Bolt",
      "chance": 16,
      "minQuantity": 60,
      "maxQuantity": 80,
      "source": "ammo_t3"
    },
    {
      "name": "Ceramic Scattershot Ammo",
      "chance": 16,
      "minQuantity": 60,
      "maxQuantity": 80,
      "source": "ammo_t3"
    },
    {
      "name": "Ceramic Dart",
      "chance": 40,
      "minQuantity": 120,
      "maxQuantity": 160,
      "source": "ammo_t3"
    },
    {
      "name": "Obsidian Rok",
      "chance": 12,
      "minQuantity": 12,
      "maxQuantity": 16,
      "source": "ammo_t3"
    },
    {
      "name": "Catapult Boulder",
      "chance": 16,
      "minQuantity": 18,
      "maxQuantity": 24,
      "source": "ammo_t3"
    },
    {
      "name": "Brittle Bone Boots",
      "chance": 17.7777776,
      "minQuantity": 7,
      "maxQuantity": 14,
      "source": "armors_t3"
    },
    {
      "name": "Brittle Bone Handwraps",
      "chance": 17.7777776,
      "minQuantity": 7,
      "maxQuantity": 14,
      "source": "armors_t3"
    },
    {
      "name": "Brittle Bone Armor",
      "chance": 17.7777776,
      "minQuantity": 7,
      "maxQuantity": 14,
      "source": "armors_t3"
    },
    {
      "name": "Carapace Boots",
      "chance": 17.7777776,
      "minQuantity": 7,
      "maxQuantity": 14,
      "source": "armors_t3"
    },
    {
      "name": "Carapace Gauntlets",
      "chance": 17.7777776,
      "minQuantity": 7,
      "maxQuantity": 14,
      "source": "armors_t3"
    },
    {
      "name": "Carapace Armor",
      "chance": 17.7777776,
      "minQuantity": 7,
      "maxQuantity": 14,
      "source": "armors_t3"
    },
    {
      "name": "Redwood Boots",
      "chance": 17.7777776,
      "minQuantity": 7,
      "maxQuantity": 14,
      "source": "armors_t3"
    },
    {
      "name": "Redwood Sleeves",
      "chance": 17.7777776,
      "minQuantity": 7,
      "maxQuantity": 14,
      "source": "armors_t3"
    },
    {
      "name": "Redwood Armor",
      "chance": 17.7777776,
      "minQuantity": 7,
      "maxQuantity": 14,
      "source": "armors_t3"
    },
    {
      "name": "Firestone Axe",
      "chance": 6.25,
      "minQuantity": 8,
      "maxQuantity": 16,
      "source": "weapons_t3"
    },
    {
      "name": "Firestone Bludgeon",
      "chance": 6.25,
      "minQuantity": 8,
      "maxQuantity": 16,
      "source": "weapons_t3"
    },
    {
      "name": "Firestone Kopesh",
      "chance": 6.25,
      "minQuantity": 8,
      "maxQuantity": 16,
      "source": "weapons_t3"
    },
    {
      "name": "Ceramic Hatchet",
      "chance": 6.25,
      "minQuantity": 8,
      "maxQuantity": 16,
      "source": "weapons_t3"
    },
    {
      "name": "Short Ceramic Hoofmace",
      "chance": 6.25,
      "minQuantity": 8,
      "maxQuantity": 16,
      "source": "weapons_t3"
    },
    {
      "name": "Short Malletblade",
      "chance": 6.25,
      "minQuantity": 8,
      "maxQuantity": 16,
      "source": "weapons_t3"
    },
    {
      "name": "Firestone Hammerstaff",
      "chance": 6.25,
      "minQuantity": 8,
      "maxQuantity": 16,
      "source": "weapons_t3"
    },
    {
      "name": "Firestone Bladestaff",
      "chance": 6.25,
      "minQuantity": 8,
      "maxQuantity": 16,
      "source": "weapons_t3"
    },
    {
      "name": "Paddleblade Quarterstaff",
      "chance": 6.25,
      "minQuantity": 8,
      "maxQuantity": 16,
      "source": "weapons_t3"
    },
    {
      "name": "Throwable Aloe Bomb",
      "chance": 6.25,
      "minQuantity": 24,
      "maxQuantity": 48,
      "source": "weapons_t3"
    },
    {
      "name": "Firebomb",
      "chance": 6.25,
      "minQuantity": 24,
      "maxQuantity": 48,
      "source": "weapons_t3"
    },
    {
      "name": "Firestone Battleaxe",
      "chance": 6.25,
      "minQuantity": 8,
      "maxQuantity": 16,
      "source": "weapons_t3"
    },
    {
      "name": "Firestone Bozdogan",
      "chance": 6.25,
      "minQuantity": 8,
      "maxQuantity": 16,
      "source": "weapons_t3"
    },
    {
      "name": "Firestone Longblade",
      "chance": 6.25,
      "minQuantity": 8,
      "maxQuantity": 16,
      "source": "weapons_t3"
    },
    {
      "name": "Long Ceramic Hoofmace",
      "chance": 6.25,
      "minQuantity": 8,
      "maxQuantity": 16,
      "source": "weapons_t3"
    },
    {
      "name": "Singblade",
      "chance": 6.25,
      "minQuantity": 8,
      "maxQuantity": 16,
      "source": "weapons_t3"
    },
    {
      "name": "Bone Glue",
      "chance": 9.4117648,
      "minQuantity": 15,
      "maxQuantity": 25,
      "source": "processedresources_t3"
    },
    {
      "name": "Wooden Gear",
      "chance": 9.4117648,
      "minQuantity": 3,
      "maxQuantity": 5,
      "source": "processedresources_t3"
    },
    {
      "name": "Triple Stitch Fabric",
      "chance": 9.4117648,
      "minQuantity": 18,
      "maxQuantity": 30,
      "source": "processedresources_t3"
    },
    {
      "name": "Nomad Cloth",
      "chance": 9.4117648,
      "minQuantity": 12,
      "maxQuantity": 20,
      "source": "processedresources_t3"
    },
    {
      "name": "Leather",
      "chance": 9.4117648,
      "minQuantity": 9,
      "maxQuantity": 15,
      "source": "processedresources_t3"
    },
    {
      "name": "Aloe Gel",
      "chance": 9.4117648,
      "minQuantity": 21,
      "maxQuantity": 35,
      "source": "processedresources_t3"
    },
    {
      "name": "Clay",
      "chance": 4.7058824,
      "minQuantity": 12,
      "maxQuantity": 20,
      "source": "processedresources_t3"
    },
    {
      "name": "Ceramic Shard",
      "chance": 4.7058824,
      "minQuantity": 9,
      "maxQuantity": 15,
      "source": "processedresources_t3"
    },
    {
      "name": "Glass",
      "chance": 4.7058824,
      "minQuantity": 9,
      "maxQuantity": 15,
      "source": "processedresources_t3"
    },
    {
      "name": "Tar",
      "chance": 4.7058824,
      "minQuantity": 9,
      "maxQuantity": 15,
      "source": "processedresources_t3"
    },
    {
      "name": "Reinforced Gear",
      "chance": 4.7058824,
      "minQuantity": 3,
      "maxQuantity": 5,
      "source": "processedresources_t3"
    },
    {
      "name": "Hornet Walker Rig T2 Schematic",
      "chance": 13.3333328,
      "minQuantity": 1,
      "maxQuantity": 1,
      "source": "rigs_t3"
    },
    {
      "name": "Hornet Walker Rig T3 Schematic",
      "chance": 2.6666666400000003,
      "minQuantity": 1,
      "maxQuantity": 1,
      "source": "rigs_t3"
    },
    {
      "name": "Falco Walker Rig T2 Schematic",
      "chance": 13.3333328,
      "minQuantity": 1,
      "maxQuantity": 1,
      "source": "rigs_t3"
    },
    {
      "name": "Falco Walker Rig T3 Schematic",
      "chance": 2.6666666400000003,
      "minQuantity": 1,
      "maxQuantity": 1,
      "source": "rigs_t3"
    },
    {
      "name": "Buffalo Walker Rig T2 Schematic",
      "chance": 13.3333328,
      "minQuantity": 1,
      "maxQuantity": 1,
      "source": "rigs_t3"
    },
    {
      "name": "Buffalo Walker Rig T3 Schematic",
      "chance": 2.6666666400000003,
      "minQuantity": 1,
      "maxQuantity": 1,
      "source": "rigs_t3"
    },
    {
      "name": "Tusker Walker Rig T2 Schematic",
      "chance": 13.3333328,
      "minQuantity": 1,
      "maxQuantity": 1,
      "source": "rigs_t3"
    },
    {
      "name": "Tusker Walker Rig T3 Schematic",
      "chance": 2.6666666400000003,
      "minQuantity": 1,
      "maxQuantity": 1,
      "source": "rigs_t3"
    },
    {
      "name": "Hercul Walker Rig T2 Schematic",
      "chance": 13.3333328,
      "minQuantity": 1,
      "maxQuantity": 1,
      "source": "rigs_t3"
    },
    {
      "name": "Hercul Walker Rig T3 Schematic",
      "chance": 2.6666666400000003,
      "minQuantity": 1,
      "maxQuantity": 1,
      "source": "rigs_t3"
    }
  ],
  "originalName": "BigHotspotLoot T3"
}