{
  "name": "Chitin Plate",
  "type": "ChitinShell_C",
  "category": "Resources",
  "trade_price": 6.6,
  "stackSize": 100,
  "weight": 0.01,
  "description": "Skittering parasites make their nests between the gooey cracks. Harvesting chitin is dirty work.",
  "experiencieReward": 15,
  "crafting": [
    {
      "ingredients": [
        {
          "count": 5,
          "name": "Insects"
        }
      ],
      "station": "Stomping Station",
      "time": 25
    },
    {
      "ingredients": [
        {
          "count": 5,
          "name": "Insects"
        }
      ],
      "station": "Advanced Stomping Station",
      "time": 15
    },
    {
      "ingredients": [
        {
          "count": 5,
          "name": "Insects"
        }
      ],
      "station": "Flotillian Stomping Station",
      "time": 5
    }
  ],
  "droppedBy": [
    {
      "name": "Okkam T3",
      "chance": 100,
      "minQuantity": 1,
      "maxQuantity": 1,
      "tier": "T3"
    }
  ],
  "whereToFarm": "Found in creatures that have scales or hard plates."
}