{
  "name": "Rawbone Maul",
  "parent": "Rawbone Maul",
  "type": "TwoHandedBoneSpikedClub_C",
  "category": "Weapons",
  "trade_price": 15.8,
  "stackSize": 100,
  "weight": 4.6,
  "description": "Sharpened bone splinters are used to make this weapon deal as much damage as possible.",
  "experiencieReward": 105,
  "durability": 420,
  "crafting": [
    {
      "ingredients": [
        {
          "name": "Bone Splinter",
          "count": 9
        },
        {
          "name": "Fiber Weave",
          "count": 4
        }
      ],
      "time": 2,
      "station": "Crafting Bench"
    }
  ],
  "weaponInfo": {
    "weaponSpeed": 120,
    "weaponLength": 97,
    "damage": 47,
    "penetration": 15
  },
  "droppedBy": [
    {
      "name": "Basket Loot T2 AC",
      "chance": 0.18181818,
      "minQuantity": 1,
      "maxQuantity": 1,
      "tier": "T2"
    },
    {
      "name": "Big Hotspot Loot T2",
      "chance": 9.090909,
      "minQuantity": 8,
      "maxQuantity": 16,
      "tier": "T2"
    },
    {
      "name": "Easy Rupu Camp T2",
      "chance": 0.027272727,
      "minQuantity": 1,
      "maxQuantity": 1,
      "tier": "T2"
    },
    {
      "name": "Easy Rupu T2",
      "chance": 0.018181818,
      "minQuantity": 1,
      "maxQuantity": 1,
      "tier": "T2"
    },
    {
      "name": "Easy Rupu T2 Q",
      "chance": 0.018181818,
      "minQuantity": 1,
      "maxQuantity": 1,
      "tier": "T2"
    },
    {
      "name": "Hard Rupu Camp T2",
      "chance": 0.09090909,
      "minQuantity": 1,
      "maxQuantity": 1,
      "tier": "T2"
    },
    {
      "name": "Hard Rupu T2",
      "chance": 0.072727272,
      "minQuantity": 1,
      "maxQuantity": 1,
      "tier": "T2"
    },
    {
      "name": "Hard Rupu T2 AC",
      "chance": 0.072727272,
      "minQuantity": 1,
      "maxQuantity": 1,
      "tier": "T2"
    },
    {
      "name": "Hard Rupu T2 Q",
      "chance": 0.072727272,
      "minQuantity": 1,
      "maxQuantity": 1,
      "tier": "T2"
    },
    {
      "name": "Hotspot Loot T2",
      "chance": 0.9090909,
      "minQuantity": 1,
      "maxQuantity": 1,
      "tier": "T2"
    },
    {
      "name": "Hotspot Loot T2 AC",
      "chance": 0.9090909,
      "minQuantity": 1,
      "maxQuantity": 1,
      "tier": "T2"
    },
    {
      "name": "Hotspot Loot Windmill T2 AC",
      "chance": 0.9090909,
      "minQuantity": 1,
      "maxQuantity": 1,
      "tier": "T2"
    },
    {
      "name": "Lootbox Weapons Canyon",
      "chance": 27.272727,
      "minQuantity": 6,
      "maxQuantity": 8
    },
    {
      "name": "Medium Rupu Camp T2",
      "chance": 0.027272727,
      "minQuantity": 1,
      "maxQuantity": 1,
      "tier": "T2"
    },
    {
      "name": "Medium Rupu T2",
      "chance": 0.018181818,
      "minQuantity": 1,
      "maxQuantity": 1,
      "tier": "T2"
    },
    {
      "name": "Medium Rupu T2 Q",
      "chance": 0.018181818,
      "minQuantity": 1,
      "maxQuantity": 1,
      "tier": "T2"
    },
    {
      "name": "Treasure Chest T2",
      "chance": 10.909090800000001,
      "minQuantity": 5,
      "maxQuantity": 10,
      "tier": "T2"
    }
  ]
}