{
  "name": "Stairs 3",
  "type": "Arena_Stairs_3_C",
  "category": "Furniture",
  "weight": 20,
  "description": "Decorative wooden construction perfect for building combat arenas, stadiums and hippodromes.",
  "crafting": [
    {
      "ingredients": [
        {
          "name": "Wood",
          "count": 5
        },
        {
          "name": "Fiber",
          "count": 8
        },
        {
          "name": "Wood Shaft",
          "count": 2
        }
      ]
    }
  ],
  "structureInfo": {
    "hp": 1500,
    "type": "Soft"
  }
}