{
  "name": "Titan Walker Wings Large",
  "type": "TitanWings_T4_C",
  "category": "Walker Parts",
  "weight": 9.75,
  "description": "Generates the highest possible physical force for walker movement. Very complicated to construct due to their size.",
  "crafting": [
    {
      "ingredients": [
        {
          "count": 1,
          "name": "Flotillan Capital Walker Wing"
        }
      ]
    }
  ],
  "structureInfo": {
    "type": "Soft",
    "hp": 30500
  },
  "walkerInfo": {
    "carryCapacity": 15000
  }
}