{
  "name": "Walker Climber",
  "parent": "Construction",
  "type": "WalkerClimber_C",
  "category": "Walker Tools",
  "weight": 5,
  "description": "A buildable attachement that helps yank nomads onto a walker's deck for quick and easy boarding.",
  "experiencieReward": 78,
  "crafting": [
    {
      "ingredients": [
        {
          "count": 30,
          "name": "Wood"
        },
        {
          "count": 4,
          "name": "Wood Shaft"
        },
        {
          "count": 35,
          "name": "Fiber"
        }
      ]
    }
  ],
  "structureInfo": {
    "type": "Soft",
    "hp": 1000
  }
}